ErisPulse_InfoStats/Core.py
ErisPulse_InfoStats/__init__.py
erispulse_infostats-1.0.0.dist-info/licenses/LICENSE
erispulse_infostats-1.0.0.dist-info/METADATA
erispulse_infostats-1.0.0.dist-info/WHEEL
erispulse_infostats-1.0.0.dist-info/entry_points.txt
erispulse_infostats-1.0.0.dist-info/top_level.txt
erispulse_infostats-1.0.0.dist-info/RECORD
