Metadata-Version: 2.4
Name: ErisPulse-InfoStats
Version: 1.0.0
Summary: 信息统计模块，用于监听和统计消息事件
Author-email: wsu2059q <wsu2059@qq.com>
License: Copyright 2025 wsu2059q
Project-URL: homepage, https://github.com/wsu2059q/ErisPulse-InfoStats
Requires-Python: >=3.9
License-File: LICENSE
Dynamic: license-file
